{"version":1,"resource":"vscode-userdata:/home/lesh/.config/Code/User/settings.json","entries":[{"id":"dGdl.json","timestamp":1759145180146},{"id":"Z8Jb.json","timestamp":1759239917789},{"id":"qb5A.json","timestamp":1759239934473},{"id":"j38A.json","timestamp":1759272298108},{"id":"PdCA.json","timestamp":1759329839746},{"id":"0jxV.json","timestamp":1759329900876},{"id":"x6IQ.json","timestamp":1759329947458},{"id":"xMZK.json","timestamp":1759498357565},{"id":"FlkY.json","timestamp":1759498699889},{"id":"TIDD.json","timestamp":1759498734978},{"id":"AqWg.json","timestamp":1759499154981},{"id":"QVAG.json","timestamp":1759499269039},{"id":"r2TN.json","timestamp":1759499331850},{"id":"Mo29.json","timestamp":1759499868153},{"id":"BhKf.json","timestamp":1759500769030},{"id":"cWL7.json","timestamp":1759501002674},{"id":"fgil.json","timestamp":1759501056180},{"id":"uLYn.json","timestamp":1759501158884},{"id":"Ngqb.json","timestamp":1759501398564},{"id":"TMYI.json","timestamp":1759501468482},{"id":"1SKd.json","timestamp":1759502456840},{"id":"7iEv.json","timestamp":1759504615911},{"id":"UtWc.json","timestamp":1759504794405},{"id":"dZPn.json","timestamp":1759505827206},{"id":"oQua.json","timestamp":1759505998178},{"id":"j280.json","timestamp":1759506243351},{"id":"82b6.json","timestamp":1759506262560},{"id":"Jw6a.json","timestamp":1759506314777},{"id":"v4bl.json","timestamp":1759506831895},{"id":"IVgj.json","timestamp":1759580165825},{"id":"tTk4.json","timestamp":1759580229171}]}